CHANGES.txt
MANIFEST.in
README.rst
setup.py
src/lovely/__init__.py
src/lovely.recipe.cappuccino.egg-info/PKG-INFO
src/lovely.recipe.cappuccino.egg-info/SOURCES.txt
src/lovely.recipe.cappuccino.egg-info/dependency_links.txt
src/lovely.recipe.cappuccino.egg-info/entry_points.txt
src/lovely.recipe.cappuccino.egg-info/namespace_packages.txt
src/lovely.recipe.cappuccino.egg-info/not-zip-safe
src/lovely.recipe.cappuccino.egg-info/requires.txt
src/lovely.recipe.cappuccino.egg-info/top_level.txt
src/lovely/recipe/__init__.py
src/lovely/recipe/cappuccino/README.txt
src/lovely/recipe/cappuccino/__init__.py
src/lovely/recipe/cappuccino/builder.py
src/lovely/recipe/cappuccino/install.py
src/lovely/recipe/cappuccino/tests.py