Metadata-Version: 1.0
Name: lovely.recipe.cappuccino
Version: 0.0.4
Summary: local cappuccino setup for zc.buildout
Home-page: http://github.com/lovelysystems/lovely.recipe.cappuccino
Author: Lovely Systems
Author-email: office@lovelysystems.com
License: ZPL 2.1
Keywords: buildout recipe cappuccino javascript objectiv-j cocoa
Platform: UNKNOWN
